LICENSE.txt
MANIFEST.in
NEWS.txt
README.rst
setup.py
src/briefs_caster.egg-info/PKG-INFO
src/briefs_caster.egg-info/SOURCES.txt
src/briefs_caster.egg-info/dependency_links.txt
src/briefs_caster.egg-info/entry_points.txt
src/briefs_caster.egg-info/not-zip-safe
src/briefs_caster.egg-info/requires.txt
src/briefs_caster.egg-info/top_level.txt
src/briefscaster/__init__.py
src/briefscaster/briefcast.py
src/briefscaster/bin/bc-bs
src/briefscaster/bin/bc-compact-briefs
src/briefscaster/tests/__init__.py
src/briefscaster/tests/test_briefcast.py