Metadata-Version: 1.0
Name: briefs-caster
Version: 0.1.1
Summary: A server for exposing your briefcasts to the world
Home-page: UNKNOWN
Author: Rob Madole
Author-email: robmadole@gmail.com
License: BSD
Platform: UNKNOWN
Classifier: Development Status :: 3 - Alpha
Classifier: Intended Audience :: Developers
Classifier: License :: OSI Approved :: BSD License
Classifier: Natural Language :: English
Classifier: Operating System :: MacOS :: MacOS X
Classifier: Topic :: Software Development
